Metadata-Version: 2.1
Name: ft_package_iderighe
Version: 0.0.1
Summary: Package for counting the number of lines in files
Author-email: iderighe <iderighe@student.42.fr>
License: MIT license
Keywords: lines,file,count
Classifier: Programming Language :: Python :: 3
Classifier: License :: OSI Approved :: MIT License
Classifier: Operating System :: OS Independent
Requires-Python: >=3.10
License-File: LICENSE
